app.py
cli.py
gdax_recurring-1.0.2.dist-info/DESCRIPTION.rst
gdax_recurring-1.0.2.dist-info/METADATA
gdax_recurring-1.0.2.dist-info/RECORD
gdax_recurring-1.0.2.dist-info/WHEEL
gdax_recurring-1.0.2.dist-info/entry_points.txt
gdax_recurring-1.0.2.dist-info/metadata.json
gdax_recurring-1.0.2.dist-info/top_level.txt
