Metadata-Version: 2.0
Name: gdax-recurring
Version: 1.0.2
Summary: Automates recurring USD deposits and asset allocation for GDAX.
Home-page: https://github.com/landakram/gdax_recurring
Author: Mark Hudnall
Author-email: me@markhudnall.com
License: MIT
Platform: UNKNOWN
Classifier: Development Status :: 5 - Production/Stable
Classifier: Environment :: Console
Classifier: License :: OSI Approved :: MIT License
Classifier: Intended Audience :: End Users/Desktop
Classifier: Intended Audience :: Developers
Classifier: Intended Audience :: Information Technology
Classifier: Intended Audience :: Financial and Insurance Industry
Classifier: Topic :: Office/Business :: Financial
Classifier: Topic :: Office/Business :: Financial :: Investment
Classifier: Topic :: Security :: Cryptography
Classifier: Operating System :: OS Independent
Requires-Dist: click
Requires-Dist: GDAX (<2.0.0,>=1.0.0)
Requires-Dist: python-dateutil
Requires-Dist: requests
